mycqu/__init__.py
mycqu/_lib_wrapper/__init__.py
mycqu/_lib_wrapper/encrypt.py
mycqu/auth/__init__.py
mycqu/auth/_authorizer.py
mycqu/auth/_authserver.py
mycqu/auth/_page_parser.py
mycqu/auth/_sso.py
mycqu/card/__init__.py
mycqu/card/_help.py
mycqu/card/models/__init__.py
mycqu/card/models/bill.py
mycqu/card/models/card.py
mycqu/card/models/energy_fees.py
mycqu/card/tools.py
mycqu/course/__init__.py
mycqu/course/models/__init__.py
mycqu/course/models/course.py
mycqu/course/models/course_day_time.py
mycqu/course/models/course_timetable.py
mycqu/course/models/cqu_session.py
mycqu/course/models/cqu_session_info.py
mycqu/course/tools.py
mycqu/enroll/__init__.py
mycqu/enroll/models/__init__.py
mycqu/enroll/models/enroll_course_info.py
mycqu/enroll/models/enroll_course_item.py
mycqu/enroll/models/enroll_course_timetable.py
mycqu/enroll/tools.py
mycqu/exam/__init__.py
mycqu/exam/models/__init__.py
mycqu/exam/models/exam.py
mycqu/exam/models/invigilator.py
mycqu/exam/tools.py
mycqu/exception.py
mycqu/library/__init__.py
mycqu/library/models/__init__.py
mycqu/library/models/book_info.py
mycqu/library/tools.py
mycqu/mycqu/__init__.py
mycqu/mycqu/models/__init__.py
mycqu/mycqu/models/user.py
mycqu/mycqu/tools.py
mycqu/room/__init__.py
mycqu/room/models/__init__.py
mycqu/room/models/room.py
mycqu/room/models/room_activity_info.py
mycqu/room/models/room_course.py
mycqu/room/models/room_exam.py
mycqu/room/models/room_exam_invigilator.py
mycqu/room/models/room_temp_activity.py
mycqu/room/models/room_timetable.py
mycqu/room/tools.py
mycqu/score/__init__.py
mycqu/score/models/__init__.py
mycqu/score/models/gpa_ranking.py
mycqu/score/models/score.py
mycqu/score/tools.py
mycqu/utils/__init__.py
mycqu/utils/config.py
mycqu/utils/datetimes.py
mycqu/utils/period.py
mycqu/utils/request_transformer/__init__.py
mycqu/utils/request_transformer/models.py
mycqu/utils/request_transformer/params_mapper.py
mycqu/utils/request_transformer/request_transformer.py
mycqu-0.6.0.dist-info/LICENSE.txt
mycqu-0.6.0.dist-info/METADATA
mycqu-0.6.0.dist-info/WHEEL
mycqu-0.6.0.dist-info/RECORD
