Metadata-Version: 2.1
Name: mycqu
Version: 0.6.0
Summary: 重庆重庆大学新教务网及相关 api 的封装
Home-page: https://pymycqu.hagb.name
License: AGPL-3.0-or-later
Keywords: cqu,Chongqing University,data model
Author: Hagb
Author-email: hagb_green@qq.com
Requires-Python: >=3.7,<4.0
Classifier: Development Status :: 4 - Beta
Classifier: License :: OSI Approved :: GNU Affero General Public License v3 or later (AGPLv3+)
Classifier: Natural Language :: Chinese (Simplified)
Classifier: Operating System :: OS Independent
Classifier: Programming Language :: Python :: 3
Classifier: Programming Language :: Python :: 3.7
Classifier: Programming Language :: Python :: 3.8
Classifier: Programming Language :: Python :: 3.9
Classifier: Programming Language :: Python :: 3.10
Classifier: Programming Language :: Python :: 3.11
Classifier: Programming Language :: Python :: 3.12
Classifier: Topic :: Internet :: WWW/HTTP
Classifier: Topic :: Software Development :: Libraries
Provides-Extra: pycryptodome
Requires-Dist: pycryptodome (>=3,<4) ; extra == "pycryptodome"
Requires-Dist: pycryptodomex (>=3,<4)
Requires-Dist: pydantic (>=2,<3)
Requires-Dist: pytz
Requires-Dist: requests (>=2,<3)
Project-URL: Documentation, https://pymycqu.hagb.name
Project-URL: Repository, https://github.com/Hagb/pymycqu
